milea_accounts/__init__.py
milea_accounts/admin.py
milea_accounts/apps.py
milea_accounts/models.py
milea_accounts/settings.py
milea_accounts/setup.py
milea_accounts/tests.py
milea_accounts/views.py
milea_accounts/locale/de/LC_MESSAGES/django.mo
milea_accounts/locale/de/LC_MESSAGES/django.po
milea_accounts/migrations/0001_initial.py
milea_accounts/migrations/0002_remove_company_country_alter_contact_salutation.py
milea_accounts/migrations/0003_remove_company_is_active_remove_contact_is_active_and_more.py
milea_accounts/migrations/0004_alter_contact_company_alter_contact_email.py
milea_accounts/migrations/0005_alter_contact_email.py
milea_accounts/migrations/0006_alter_contact_email.py
milea_accounts/migrations/0007_type.py
milea_accounts/migrations/0008_alter_type_options_alter_company_type_and_more.py
milea_accounts/migrations/__init__.py
milea_accounts/migrations/__pycache__/0001_initial.cpython-311.pyc
milea_accounts/migrations/__pycache__/0002_remove_company_country_alter_contact_salutation.cpython-311.pyc
milea_accounts/migrations/__pycache__/0003_remove_company_is_active_remove_contact_is_active_and_more.cpython-311.pyc
milea_accounts/migrations/__pycache__/0004_alter_contact_company_alter_contact_email.cpython-311.pyc
milea_accounts/migrations/__pycache__/0005_alter_contact_email.cpython-311.pyc
milea_accounts/migrations/__pycache__/0006_alter_contact_email.cpython-311.pyc
milea_accounts/migrations/__pycache__/0007_type.cpython-311.pyc
milea_accounts/migrations/__pycache__/0008_alter_type_options_alter_company_type_and_more.cpython-311.pyc
milea_accounts/migrations/__pycache__/__init__.cpython-311.pyc
milea_accounts-0.2.dist-info/METADATA
milea_accounts-0.2.dist-info/WHEEL
milea_accounts-0.2.dist-info/top_level.txt
milea_accounts-0.2.dist-info/RECORD
